formidable/__init__.py
formidable/common.py
formidable/errors.py
formidable/form.py
formidable/parser.py
formidable/wrappers.py
formidable/fields/__init__.py
formidable/fields/base.py
formidable/fields/boolean.py
formidable/fields/date.py
formidable/fields/datetime.py
formidable/fields/email.py
formidable/fields/file.py
formidable/fields/formfield.py
formidable/fields/list.py
formidable/fields/nested.py
formidable/fields/number.py
formidable/fields/slug.py
formidable/fields/text.py
formidable/fields/time.py
formidable/fields/url.py
formidable-0.14.dist-info/METADATA
formidable-0.14.dist-info/WHEEL
formidable-0.14.dist-info/top_level.txt
formidable-0.14.dist-info/RECORD
