Metadata-Version: 2.4
Name: formidable
Version: 0.14
Summary: Small but powerful library for rendering and processing web forms
Author-email: Juan-Pablo Scaletti <juanpablo@jpscaletti.com>
License-Expression: MIT
Project-URL: Code, https://github.com/jpsca/formidable
Project-URL: Documentation, https://formidable.scaletti.dev/
Classifier: Development Status :: 4 - Beta
Classifier: Environment :: Web Environment
Classifier: Intended Audience :: Developers
Classifier: Programming Language :: Python :: 3 :: Only
Classifier: Programming Language :: Python :: 3.12
Classifier: Programming Language :: Python :: 3.13
Classifier: Programming Language :: Python :: 3.14
Classifier: Typing :: Typed
Requires-Python: <4,>=3.12
Requires-Dist: idna>=3.10
Requires-Dist: markupsafe>=3.0.3
Provides-Extra: email
Requires-Dist: email-validator~=2.3.0; extra == "email"
